{
  "url": "https://api.github.com/repos/quarkusio/quarkus/issues/20957",
  "repository_url": "https://api.github.com/repos/quarkusio/quarkus",
  "labels_url": "https://api.github.com/repos/quarkusio/quarkus/issues/20957/labels{/name}",
  "comments_url": "https://api.github.com/repos/quarkusio/quarkus/issues/20957/comments",
  "events_url": "https://api.github.com/repos/quarkusio/quarkus/issues/20957/events",
  "html_url": "https://github.com/quarkusio/quarkus/issues/20957",
  "id": 1034133233,
  "node_id": "I_kwDOCFbutM49o57x",
  "number": 20957,
  "title": "Hot-reload fails with ConfigMapping in ContainerRequestFilter",
  "labels": [
    {
      "id": 985346620,
      "node_id": "MDU6TGFiZWw5ODUzNDY2MjA=",
      "url": "https://api.github.com/repos/quarkusio/quarkus/labels/kind/bug",
      "name": "kind/bug",
      "color": "d73a4a",
      "default": false,
      "description": "Something isn't working"
    },
    {
      "id": 1273030910,
      "node_id": "MDU6TGFiZWwxMjczMDMwOTEw",
      "url": "https://api.github.com/repos/quarkusio/quarkus/labels/area/config",
      "name": "area/config",
      "color": "0366d6",
      "default": false,
      "description": ""
    },
    {
      "id": 1676631606,
      "node_id": "MDU6TGFiZWwxNjc2NjMxNjA2",
      "url": "https://api.github.com/repos/quarkusio/quarkus/labels/env/windows",
      "name": "env/windows",
      "color": "edea47",
      "default": false,
      "description": "Impacts Windows machines"
    }
  ],
  "state": "closed",
  "locked": false,
  "milestone": {
    "url": "https://api.github.com/repos/quarkusio/quarkus/milestones/156",
    "html_url": "https://github.com/quarkusio/quarkus/milestone/156",
    "labels_url": "https://api.github.com/repos/quarkusio/quarkus/milestones/156/labels",
    "id": 7270553,
    "node_id": "MI_kwDOCFbutM4AbvCZ",
    "number": 156,
    "title": "2.4.1.Final",
    "description": "",
    "creator": {
      "login": "aloubyansky",
      "id": 323379,
      "node_id": "MDQ6VXNlcjMyMzM3OQ==",
      "avatar_url": "https://avatars.githubusercontent.com/u/323379?v=4",
      "gravatar_id": "",
      "url": "https://api.github.com/users/aloubyansky",
      "html_url": "https://github.com/aloubyansky",
      "followers_url": "https://api.github.com/users/aloubyansky/followers",
      "following_url": "https://api.github.com/users/aloubyansky/following{/other_user}",
      "gists_url": "https://api.github.com/users/aloubyansky/gists{/gist_id}",
      "starred_url": "https://api.github.com/users/aloubyansky/starred{/owner}{/repo}",
      "subscriptions_url": "https://api.github.com/users/aloubyansky/subscriptions",
      "organizations_url": "https://api.github.com/users/aloubyansky/orgs",
      "repos_url": "https://api.github.com/users/aloubyansky/repos",
      "events_url": "https://api.github.com/users/aloubyansky/events{/privacy}",
      "received_events_url": "https://api.github.com/users/aloubyansky/received_events",
      "type": "User",
      "site_admin": false
    },
    "open_issues": 0,
    "closed_issues": 87,
    "state": "closed",
    "created_at": "2021-10-20T06:35:24Z",
    "updated_at": "2021-11-11T13:31:49Z",
    "due_on": null,
    "closed_at": "2021-11-03T11:29:46Z"
  },
  "comments": 1,
  "created_at": "2021-10-23T10:20:07Z",
  "updated_at": "2021-11-02T10:38:27Z",
  "closed_at": "2021-10-27T10:02:26Z",
  "active_lock_reason": null,
  "body": "### Describe the bug\r\n\r\nI'm injecting a ConfigMapping in a ContainerRequestFilter. The initial application startup works and I can invoke my REST endpoints without any problems. When I make a change to the code, quarkus hot-reloads upon the next request but the reload fails.\r\n\r\n### Expected behavior\r\n\r\nHot-reload should load the config the same way as the initial load does.\r\n\r\n### Actual behavior\r\n\r\nUpon hot-reload I see a NoSuchElementException:\r\n\r\n`Caused by: java.util.NoSuchElementException: SRCFG00027: Could not find a mapping for org.acme.MyConfig\r\n        at io.smallrye.config.ConfigMappings.getConfigMapping(ConfigMappings.java:100)\r\n        at io.smallrye.config.SmallRyeConfig.getConfigMapping(SmallRyeConfig.java:398)\r\n        at io.quarkus.arc.runtime.ConfigMappingCreator.create(ConfigMappingCreator.java:28)\r\n        at org.acme.MyConfig_bcfb30ea94df0bb5f64f23dfaa52b4e519ed945b_Synthetic_Bean.create(MyConfig_bcfb30ea94df0bb5f64f23dfaa52b4e519ed945b_S                                                                                                ynthetic_Bean.zig:128)\r\n        at org.acme.MyConfig_bcfb30ea94df0bb5f64f23dfaa52b4e519ed945b_Synthetic_Bean.get(MyConfig_bcfb30ea94df0bb5f64f23dfaa52b4e519ed945b_Synthetic_Bean.zig:159)\r\n        at org.acme.MyConfig_bcfb30ea94df0bb5f64f23dfaa52b4e519ed945b_Synthetic_Bean.get(MyConfig_bcfb30ea94df0bb5f64f23dfaa52b4e519ed945b_Synthetic_Bean.zig:182)\r\n        at io.quarkus.arc.impl.CurrentInjectionPointProvider.get(CurrentInjectionPointProvider.java:52)\r\n        at org.acme.MyFilter_Bean.create(MyFilter_Bean.zig:241)\r\n        ... 57 more`\r\n\r\n### How to Reproduce?\r\n\r\nI've created a [minimal reproducer](https://github.com/quarkusio/quarkus/files/7402665/config-mapping-bug.zip) with just one resource, filter, ConfigMapping and properties file.\r\n\r\nRun it in dev mode and get the /hello path. That works. Then make any change to the code and try again. That won’t work. \r\n\r\n\r\n### Output of `uname -a` or `ver`\r\n\r\nMicrosoft Windows [Version 10.0.19042.1237]\r\n\r\n### Output of `java -version`\r\n\r\nopenjdk version \"17\" 2021-09-14 OpenJDK Runtime Environment (build 17+35-2724) OpenJDK 64-Bit Server VM (build 17+35-2724, mixed mode, sharing)\r\n\r\n### GraalVM version (if different from Java)\r\n\r\n_No response_\r\n\r\n### Quarkus version or git rev\r\n\r\n2.3.1.FINAL\r\n\r\n### Build tool (ie. output of `mvnw --version` or `gradlew --version`)\r\n\r\nMaven home: C:\\Users\\morit\\.m2\\wrapper\\dists\\apache-maven-3.8.1-bin\\2l5mhf2pq2clrde7f7qp1rdt5m\\apache-maven-3.8.1 Java version: 17, vendor: Oracle Corporation, runtime: C:\\Users\\morit\\scoop\\apps\\openjdk17\\current Default locale: en_US, platform encoding: Cp1252 OS name: \"windows 10\", version: \"10.0\", arch: \"amd64\", family: \"windows\"\r\n\r\n### Additional information\r\n\r\n_No response_",
  "reactions": {
    "url": "https://api.github.com/repos/quarkusio/quarkus/issues/20957/reactions",
    "total_count": 0,
    "+1": 0,
    "-1": 0,
    "laugh": 0,
    "hooray": 0,
    "confused": 0,
    "heart": 0,
    "rocket": 0,
    "eyes": 0
  },
  "timeline_url": "https://api.github.com/repos/quarkusio/quarkus/issues/20957/timeline",
  "performed_via_github_app": null,
  "state_reason": "completed"
}
