{
  "url": "https://api.github.com/repos/quarkusio/quarkus/issues/22910",
  "repository_url": "https://api.github.com/repos/quarkusio/quarkus",
  "labels_url": "https://api.github.com/repos/quarkusio/quarkus/issues/22910/labels{/name}",
  "comments_url": "https://api.github.com/repos/quarkusio/quarkus/issues/22910/comments",
  "events_url": "https://api.github.com/repos/quarkusio/quarkus/issues/22910/events",
  "html_url": "https://github.com/quarkusio/quarkus/issues/22910",
  "id": 1103898984,
  "node_id": "I_kwDOCFbutM5BzClo",
  "number": 22910,
  "title": "Custom ConfigSourceInterceptor makes build fail",
  "labels": [
    {
      "id": 985346620,
      "node_id": "MDU6TGFiZWw5ODUzNDY2MjA=",
      "url": "https://api.github.com/repos/quarkusio/quarkus/labels/kind/bug",
      "name": "kind/bug",
      "color": "d73a4a",
      "default": false,
      "description": "Something isn't working"
    },
    {
      "id": 1273030910,
      "node_id": "MDU6TGFiZWwxMjczMDMwOTEw",
      "url": "https://api.github.com/repos/quarkusio/quarkus/labels/area/config",
      "name": "area/config",
      "color": "0366d6",
      "default": false,
      "description": ""
    },
    {
      "id": 1282136257,
      "node_id": "MDU6TGFiZWwxMjgyMTM2MjU3",
      "url": "https://api.github.com/repos/quarkusio/quarkus/labels/area/maven",
      "name": "area/maven",
      "color": "0366d6",
      "default": false,
      "description": ""
    }
  ],
  "state": "closed",
  "locked": false,
  "milestone": {
    "url": "https://api.github.com/repos/quarkusio/quarkus/milestones/161",
    "html_url": "https://github.com/quarkusio/quarkus/milestone/161",
    "labels_url": "https://api.github.com/repos/quarkusio/quarkus/milestones/161/labels",
    "id": 7468359,
    "node_id": "MI_kwDOCFbutM4AcfVH",
    "number": 161,
    "title": "2.7.0.CR1",
    "description": "",
    "creator": {
      "login": "gsmet",
      "id": 1279749,
      "node_id": "MDQ6VXNlcjEyNzk3NDk=",
      "avatar_url": "https://avatars.githubusercontent.com/u/1279749?v=4",
      "gravatar_id": "",
      "url": "https://api.github.com/users/gsmet",
      "html_url": "https://github.com/gsmet",
      "followers_url": "https://api.github.com/users/gsmet/followers",
      "following_url": "https://api.github.com/users/gsmet/following{/other_user}",
      "gists_url": "https://api.github.com/users/gsmet/gists{/gist_id}",
      "starred_url": "https://api.github.com/users/gsmet/starred{/owner}{/repo}",
      "subscriptions_url": "https://api.github.com/users/gsmet/subscriptions",
      "organizations_url": "https://api.github.com/users/gsmet/orgs",
      "repos_url": "https://api.github.com/users/gsmet/repos",
      "events_url": "https://api.github.com/users/gsmet/events{/privacy}",
      "received_events_url": "https://api.github.com/users/gsmet/received_events",
      "type": "User",
      "site_admin": false
    },
    "open_issues": 0,
    "closed_issues": 334,
    "state": "closed",
    "created_at": "2021-12-08T07:48:18Z",
    "updated_at": "2022-02-03T19:52:11Z",
    "due_on": null,
    "closed_at": "2022-01-19T12:42:36Z"
  },
  "comments": 4,
  "created_at": "2022-01-14T16:50:57Z",
  "updated_at": "2022-01-28T11:47:01Z",
  "closed_at": "2022-01-18T06:50:07Z",
  "active_lock_reason": null,
  "body": "### Describe the bug\n\nAdding a custom ConfigSourceInterceptor to a quarkus app makes the build fail with the following stack trace during the `generate-code` phase:\r\n```\r\nCaused by: java.util.ServiceConfigurationError: io.smallrye.config.ConfigSourceInterceptor: Provider com.mycompany.config.MyConfigSourceInterceptor not found\r\n    at java.util.ServiceLoader.fail (ServiceLoader.java:593)\r\n    at java.util.ServiceLoader$LazyClassPathLookupIterator.nextProviderClass (ServiceLoader.java:1219)\r\n    at java.util.ServiceLoader$LazyClassPathLookupIterator.hasNextService (ServiceLoader.java:1228)\r\n    at java.util.ServiceLoader$LazyClassPathLookupIterator.hasNext (ServiceLoader.java:1273)\r\n    at java.util.ServiceLoader$2.hasNext (ServiceLoader.java:1309)\r\n    at java.util.ServiceLoader$3.hasNext (ServiceLoader.java:1393)\r\n    at io.smallrye.config.SmallRyeConfigBuilder.discoverInterceptors (SmallRyeConfigBuilder.java:131)\r\n    at io.smallrye.config.SmallRyeConfig$ConfigSources.buildInterceptors (SmallRyeConfig.java:568)\r\n    at io.smallrye.config.SmallRyeConfig$ConfigSources.<init> (SmallRyeConfig.java:516)\r\n    at io.smallrye.config.SmallRyeConfig.<init> (SmallRyeConfig.java:66)\r\n    at io.smallrye.config.SmallRyeConfigBuilder.build (SmallRyeConfigBuilder.java:419)\r\n    at io.quarkus.deployment.CodeGenerator.lambda$trigger$1 (CodeGenerator.java:98)\r\n    at io.quarkus.deployment.CodeGenerator.callWithClassloader (CodeGenerator.java:70)\r\n    at io.quarkus.deployment.CodeGenerator.trigger (CodeGenerator.java:91)\r\n    at io.quarkus.deployment.CodeGenerator.initAndRun (CodeGenerator.java:34)\r\n    at jdk.internal.reflect.NativeMethodAccessorImpl.invoke0 (Native Method)\r\n    at jdk.internal.reflect.NativeMethodAccessorImpl.invoke (NativeMethodAccessorImpl.java:77)\r\n    at jdk.internal.reflect.DelegatingMethodAccessorImpl.invoke (DelegatingMethodAccessorImpl.java:43)\r\n    at java.lang.reflect.Method.invoke (Method.java:568)\r\n    at io.quarkus.maven.GenerateCodeMojo.generateCode (GenerateCodeMojo.java:79)\r\n    at io.quarkus.maven.GenerateCodeMojo.doExecute (GenerateCodeMojo.java:54)\r\n    at io.quarkus.maven.QuarkusBootstrapMojo.execute (QuarkusBootstrapMojo.java:123)\r\n    at org.apache.maven.plugin.DefaultBuildPluginManager.executeMojo (DefaultBuildPluginManager.java:137)\r\n    at org.apache.maven.lifecycle.internal.MojoExecutor.execute (MojoExecutor.java:210)\r\n    at org.apache.maven.lifecycle.internal.MojoExecutor.execute (MojoExecutor.java:156)\r\n    at org.apache.maven.lifecycle.internal.MojoExecutor.execute (MojoExecutor.java:148)\r\n    at org.apache.maven.lifecycle.internal.LifecycleModuleBuilder.buildProject (LifecycleModuleBuilder.java:117)\r\n    at org.apache.maven.lifecycle.internal.LifecycleModuleBuilder.buildProject (LifecycleModuleBuilder.java:81)\r\n    at org.apache.maven.lifecycle.internal.builder.singlethreaded.SingleThreadedBuilder.build (SingleThreadedBuilder.java:56)\r\n    at org.apache.maven.lifecycle.internal.LifecycleStarter.execute (LifecycleStarter.java:128)\r\n    at org.apache.maven.DefaultMaven.doExecute (DefaultMaven.java:305)\r\n    at org.apache.maven.DefaultMaven.doExecute (DefaultMaven.java:192)\r\n    at org.apache.maven.DefaultMaven.execute (DefaultMaven.java:105)\r\n    at org.apache.maven.cli.MavenCli.execute (MavenCli.java:957)\r\n    at org.apache.maven.cli.MavenCli.doMain (MavenCli.java:289)\r\n    at org.apache.maven.cli.MavenCli.main (MavenCli.java:193)\r\n    at jdk.internal.reflect.NativeMethodAccessorImpl.invoke0 (Native Method)\r\n    at jdk.internal.reflect.NativeMethodAccessorImpl.invoke (NativeMethodAccessorImpl.java:77)\r\n    at jdk.internal.reflect.DelegatingMethodAccessorImpl.invoke (DelegatingMethodAccessorImpl.java:43)\r\n    at java.lang.reflect.Method.invoke (Method.java:568)\r\n    at org.codehaus.plexus.classworlds.launcher.Launcher.launchEnhanced (Launcher.java:282)\r\n    at org.codehaus.plexus.classworlds.launcher.Launcher.launch (Launcher.java:225)\r\n    at org.codehaus.plexus.classworlds.launcher.Launcher.mainWithExitCode (Launcher.java:406)\r\n    at org.codehaus.plexus.classworlds.launcher.Launcher.main (Launcher.java:347)\r\n    at jdk.internal.reflect.NativeMethodAccessorImpl.invoke0 (Native Method)\r\n    at jdk.internal.reflect.NativeMethodAccessorImpl.invoke (NativeMethodAccessorImpl.java:77)\r\n    at jdk.internal.reflect.DelegatingMethodAccessorImpl.invoke (DelegatingMethodAccessorImpl.java:43)\r\n    at java.lang.reflect.Method.invoke (Method.java:568)\r\n    at org.apache.maven.wrapper.BootstrapMainStarter.start (BootstrapMainStarter.java:39)\r\n    at org.apache.maven.wrapper.WrapperExecutor.execute (WrapperExecutor.java:122)\r\n    at org.apache.maven.wrapper.MavenWrapperMain.main (MavenWrapperMain.java:61)\r\n\r\n```\r\n\r\nThis is expected since at this point the class defined in the service loader file has not been compiled yet as discussed with @radcortez at https://quarkusio.zulipchat.com/#narrow/stream/294206-smallrye/topic/configsourceinterceptor\n\n### Expected behavior\n\nThe quarkus maven plugin does not try to load custom ConfigSourceProvider during application build.\n\n### Actual behavior\n\nThe quarkus maven plugin tries to load the custom ConfigSourceProvider that are supposed to be compiled later.\n\n### How to Reproduce?\n\n1. Create a project\r\n2. Add a custom ConfigSourceProvider\r\n3. Run `mvn clean package`\r\n\r\nI tried reproducing it in a dedicated test project but without success, I have not been able to identify which conditions would reproduce the issue.\n\n### Output of `uname -a` or `ver`\n\nDarwin XXXX 21.2.0 Darwin Kernel Version 21.2.0: Sun Nov 28 20:28:54 PST 2021; root:xnu-8019.61.5~1/RELEASE_X86_64 x86_64\n\n### Output of `java -version`\n\nopenjdk version \"17.0.1\" 2021-10-19 OpenJDK Runtime Environment GraalVM CE 21.3.0 (build 17.0.1+12-jvmci-21.3-b05) OpenJDK 64-Bit Server VM GraalVM CE 21.3.0 (build 17.0.1+12-jvmci-21.3-b05, mixed mode, sharing)\n\n### GraalVM version (if different from Java)\n\n_No response_\n\n### Quarkus version or git rev\n\n2.6.2.Final\n\n### Build tool (ie. output of `mvnw --version` or `gradlew --version`)\n\nApache Maven 3.8.3 (ff8e977a158738155dc465c6a97ffaf31982d739)\n\n### Additional information\n\n_No response_",
  "reactions": {
    "url": "https://api.github.com/repos/quarkusio/quarkus/issues/22910/reactions",
    "total_count": 0,
    "+1": 0,
    "-1": 0,
    "laugh": 0,
    "hooray": 0,
    "confused": 0,
    "heart": 0,
    "rocket": 0,
    "eyes": 0
  },
  "timeline_url": "https://api.github.com/repos/quarkusio/quarkus/issues/22910/timeline",
  "performed_via_github_app": null,
  "state_reason": "completed"
}
