{
  "url": "https://api.github.com/repos/quarkusio/quarkus/issues/24613",
  "repository_url": "https://api.github.com/repos/quarkusio/quarkus",
  "labels_url": "https://api.github.com/repos/quarkusio/quarkus/issues/24613/labels{/name}",
  "comments_url": "https://api.github.com/repos/quarkusio/quarkus/issues/24613/comments",
  "events_url": "https://api.github.com/repos/quarkusio/quarkus/issues/24613/events",
  "html_url": "https://github.com/quarkusio/quarkus/issues/24613",
  "id": 1185310455,
  "node_id": "I_kwDOCFbutM5Gpmb3",
  "number": 24613,
  "title": "Regression: Quarkus-cli create app doesn't auto-detect Host java version",
  "labels": [
    {
      "id": 985346620,
      "node_id": "MDU6TGFiZWw5ODUzNDY2MjA=",
      "url": "https://api.github.com/repos/quarkusio/quarkus/labels/kind/bug",
      "name": "kind/bug",
      "color": "d73a4a",
      "default": false,
      "description": "Something isn't working"
    },
    {
      "id": 2313298528,
      "node_id": "MDU6TGFiZWwyMzEzMjk4NTI4",
      "url": "https://api.github.com/repos/quarkusio/quarkus/labels/area/cli",
      "name": "area/cli",
      "color": "0366d6",
      "default": false,
      "description": "Related to quarkus cli (not maven/gradle/etc.)"
    },
    {
      "id": 2323889171,
      "node_id": "MDU6TGFiZWwyMzIzODg5MTcx",
      "url": "https://api.github.com/repos/quarkusio/quarkus/labels/area/jbang",
      "name": "area/jbang",
      "color": "0052cc",
      "default": false,
      "description": "Issues related to when using jbang.dev with Quarkus"
    }
  ],
  "state": "closed",
  "locked": false,
  "milestone": {
    "url": "https://api.github.com/repos/quarkusio/quarkus/milestones/184",
    "html_url": "https://github.com/quarkusio/quarkus/milestone/184",
    "labels_url": "https://api.github.com/repos/quarkusio/quarkus/milestones/184/labels",
    "id": 7922797,
    "node_id": "MI_kwDOCFbutM4AeORt",
    "number": 184,
    "title": "2.7.6.Final",
    "description": "",
    "creator": {
      "login": "gsmet",
      "id": 1279749,
      "node_id": "MDQ6VXNlcjEyNzk3NDk=",
      "avatar_url": "https://avatars.githubusercontent.com/u/1279749?v=4",
      "gravatar_id": "",
      "url": "https://api.github.com/users/gsmet",
      "html_url": "https://github.com/gsmet",
      "followers_url": "https://api.github.com/users/gsmet/followers",
      "following_url": "https://api.github.com/users/gsmet/following{/other_user}",
      "gists_url": "https://api.github.com/users/gsmet/gists{/gist_id}",
      "starred_url": "https://api.github.com/users/gsmet/starred{/owner}{/repo}",
      "subscriptions_url": "https://api.github.com/users/gsmet/subscriptions",
      "organizations_url": "https://api.github.com/users/gsmet/orgs",
      "repos_url": "https://api.github.com/users/gsmet/repos",
      "events_url": "https://api.github.com/users/gsmet/events{/privacy}",
      "received_events_url": "https://api.github.com/users/gsmet/received_events",
      "type": "User",
      "site_admin": false
    },
    "open_issues": 0,
    "closed_issues": 171,
    "state": "closed",
    "created_at": "2022-04-28T08:08:41Z",
    "updated_at": "2022-05-30T11:25:22Z",
    "due_on": null,
    "closed_at": "2022-05-30T11:25:22Z"
  },
  "comments": 11,
  "created_at": "2022-03-29T19:21:01Z",
  "updated_at": "2022-05-12T08:11:43Z",
  "closed_at": "2022-03-31T15:23:24Z",
  "active_lock_reason": null,
  "body": "### Describe the bug\r\n\r\nWhen you create an app with `Quarkus-cli 2.6.3` the tool detects the java version that is running in the developer environment and the resulted app has the same java version as the host. \r\n\r\nThis feature is broken in `Quarkus 2.7.5.Final`\r\n\r\nReproducer: \r\n\r\nQuarkus 2.6.3\r\n\r\nInstall quarkus-cli 2.6.3: `jbang app install --name qs2.6.3 io.quarkus:quarkus-cli:2.6.3.Final:runner `\r\nCreate app: `qs2.6.3 create app app`\r\n\r\nThe pom has the same Java version as the host machine. \r\n\r\nQuarkus 2.7.5\r\n\r\nInstall quarkus-cli 2.6.3:  `jbang app install --name qs2.7.5 io.quarkus:quarkus-cli:2.7.5.Final:runner `\r\nCreate app: `qs2.7.5 create app app`\r\nPom Java version:`<maven.compiler.release>11</maven.compiler.release> `\r\nExpected version: `17`\r\n\r\n\r\n### Output of `java -version`\r\n\r\nopenjdk 17.0.1 2021-10-19 OpenJDK Runtime Environment Temurin-17.0.1+12 (build 17.0.1+12) OpenJDK 64-Bit Server VM Temurin-17.0.1+12 (build 17.0.1+12, mixed mode, sharing)\r\n\r\n",
  "reactions": {
    "url": "https://api.github.com/repos/quarkusio/quarkus/issues/24613/reactions",
    "total_count": 0,
    "+1": 0,
    "-1": 0,
    "laugh": 0,
    "hooray": 0,
    "confused": 0,
    "heart": 0,
    "rocket": 0,
    "eyes": 0
  },
  "timeline_url": "https://api.github.com/repos/quarkusio/quarkus/issues/24613/timeline",
  "performed_via_github_app": null,
  "state_reason": "completed"
}
