{
  "url": "https://api.github.com/repos/quarkusio/quarkus/issues/25389",
  "repository_url": "https://api.github.com/repos/quarkusio/quarkus",
  "labels_url": "https://api.github.com/repos/quarkusio/quarkus/issues/25389/labels{/name}",
  "comments_url": "https://api.github.com/repos/quarkusio/quarkus/issues/25389/comments",
  "events_url": "https://api.github.com/repos/quarkusio/quarkus/issues/25389/events",
  "html_url": "https://github.com/quarkusio/quarkus/issues/25389",
  "id": 1226325985,
  "node_id": "I_kwDOCFbutM5JGD_h",
  "number": 25389,
  "title": "Add togglz extension",
  "labels": [
    {
      "id": 1553869078,
      "node_id": "MDU6TGFiZWwxNTUzODY5MDc4",
      "url": "https://api.github.com/repos/quarkusio/quarkus/labels/kind/extension-proposal",
      "name": "kind/extension-proposal",
      "color": "abfcbb",
      "default": false,
      "description": "Discuss and Propose new extensions"
    },
    {
      "id": 2388070055,
      "node_id": "MDU6TGFiZWwyMzg4MDcwMDU1",
      "url": "https://api.github.com/repos/quarkusio/quarkus/labels/area/quarkiverse",
      "name": "area/quarkiverse",
      "color": "a01441",
      "default": false,
      "description": "This issue/PR is part of the Quarkiverse organization"
    }
  ],
  "state": "closed",
  "locked": false,
  "milestone": null,
  "comments": 6,
  "created_at": "2022-05-05T08:04:20Z",
  "updated_at": "2023-09-13T18:18:09Z",
  "closed_at": "2022-05-05T14:38:21Z",
  "active_lock_reason": null,
  "body": "### Description\n\nInterested in this extension, please +1 via the emoji/reaction feature of GitHub (top right).\n\n### Configuration suggestion\n\n_No response_\n\n### Additional context\n\nDear co-workers :) \r\n\r\nIt's on my list since a while.. I would like to add a quarkiverse extension for \"my\" Open Source project called [togglz](https://github.com/togglz/togglz)\r\n\r\nIt's a Feature Flag / Feature Toggle library in Java and besides [Unleash](https://quarkiverse.github.io/quarkiverse-docs/quarkus-unleash/dev/index.html) which is an alternative library for Feature Flags (it's a bit different from an architectural approach) it would be good to have an alternative to it when using Quarkus.",
  "reactions": {
    "url": "https://api.github.com/repos/quarkusio/quarkus/issues/25389/reactions",
    "total_count": 0,
    "+1": 0,
    "-1": 0,
    "laugh": 0,
    "hooray": 0,
    "confused": 0,
    "heart": 0,
    "rocket": 0,
    "eyes": 0
  },
  "timeline_url": "https://api.github.com/repos/quarkusio/quarkus/issues/25389/timeline",
  "performed_via_github_app": null,
  "state_reason": "completed"
}
