{
  "url": "https://api.github.com/repos/quarkusio/quarkus/issues/25426",
  "repository_url": "https://api.github.com/repos/quarkusio/quarkus",
  "labels_url": "https://api.github.com/repos/quarkusio/quarkus/issues/25426/labels{/name}",
  "comments_url": "https://api.github.com/repos/quarkusio/quarkus/issues/25426/comments",
  "events_url": "https://api.github.com/repos/quarkusio/quarkus/issues/25426/events",
  "html_url": "https://github.com/quarkusio/quarkus/issues/25426",
  "id": 1228091252,
  "node_id": "I_kwDOCFbutM5JMy90",
  "number": 25426,
  "title": "Including undertow extension disables devmode NotFound Exception Mapper",
  "labels": [
    {
      "id": 985346620,
      "node_id": "MDU6TGFiZWw5ODUzNDY2MjA=",
      "url": "https://api.github.com/repos/quarkusio/quarkus/labels/kind/bug",
      "name": "kind/bug",
      "color": "d73a4a",
      "default": false,
      "description": "Something isn't working"
    },
    {
      "id": 1273039603,
      "node_id": "MDU6TGFiZWwxMjczMDM5NjAz",
      "url": "https://api.github.com/repos/quarkusio/quarkus/labels/area/devmode",
      "name": "area/devmode",
      "color": "0366d6",
      "default": false,
      "description": ""
    },
    {
      "id": 1359391180,
      "node_id": "MDU6TGFiZWwxMzU5MzkxMTgw",
      "url": "https://api.github.com/repos/quarkusio/quarkus/labels/area/undertow",
      "name": "area/undertow",
      "color": "0366d6",
      "default": false,
      "description": ""
    }
  ],
  "state": "open",
  "locked": false,
  "milestone": null,
  "comments": 3,
  "created_at": "2022-05-06T16:57:54Z",
  "updated_at": "2022-05-09T05:38:29Z",
  "closed_at": null,
  "active_lock_reason": null,
  "body": "### Describe the bug\n\n2.8.2.Final\r\n\r\nDev mode includes a handy NotFound exception mapper that shows all the endpoints available\r\nIf one includes the `undertow` extension, this seems to disable/prevent this special error page\n\n### Expected behavior\n\nShould show the exception mapper (as it shows without the `undertow` extension)\r\n\r\n![image](https://user-images.githubusercontent.com/887008/167177515-4fa7f9e4-89cc-4541-9044-b8496525a908.png)\r\n\n\n### Actual behavior\n\nDisplays `Not Found` text\r\n\r\n![image](https://user-images.githubusercontent.com/887008/167177765-f7b1f240-a8f8-473c-ae5f-978df4c519f4.png)\r\n\n\n### How to Reproduce?\n\nSteps to reproduce:\r\n\r\n1. Create a new project with `quarkus-resteasy-reactive` and `quarkus-resteasy-reactive-jackson` extensions with sample code\r\n2. Add the `undertow` extension\r\n3. Navigate to a url that should produce a 404\n\n### Output of `uname -a` or `ver`\n\nDarwin Yoels-MacBook-Pro 21.4.0 Darwin Kernel Version 21.4.0: Fri Mar 18 00:45:05 PDT 2022; root:xnu-8020.101.4~15/RELEASE_X86_64 x86_64\n\n### Output of `java -version`\n\nopenjdk version \"11.0.14\" 2022-01-18 OpenJDK Runtime Environment GraalVM CE 22.0.0.2 (build 11.0.14+9-jvmci-22.0-b05) OpenJDK 64-Bit Server VM GraalVM CE 22.0.0.2 (build 11.0.14+9-jvmci-22.0-b05, mixed mode, sharing)\n\n### GraalVM version (if different from Java)\n\n22.0.0.2.r11\n\n### Quarkus version or git rev\n\n2.8.2.Final\n\n### Build tool (ie. output of `mvnw --version` or `gradlew --version`)\n\n7.4.1\n\n### Additional information\n\n_No response_",
  "reactions": {
    "url": "https://api.github.com/repos/quarkusio/quarkus/issues/25426/reactions",
    "total_count": 1,
    "+1": 1,
    "-1": 0,
    "laugh": 0,
    "hooray": 0,
    "confused": 0,
    "heart": 0,
    "rocket": 0,
    "eyes": 0
  },
  "timeline_url": "https://api.github.com/repos/quarkusio/quarkus/issues/25426/timeline",
  "performed_via_github_app": null,
  "state_reason": null
}
