{
  "url": "https://api.github.com/repos/quarkusio/quarkus/issues/29922",
  "repository_url": "https://api.github.com/repos/quarkusio/quarkus",
  "labels_url": "https://api.github.com/repos/quarkusio/quarkus/issues/29922/labels{/name}",
  "comments_url": "https://api.github.com/repos/quarkusio/quarkus/issues/29922/comments",
  "events_url": "https://api.github.com/repos/quarkusio/quarkus/issues/29922/events",
  "html_url": "https://github.com/quarkusio/quarkus/issues/29922",
  "id": 1500142328,
  "node_id": "I_kwDOCFbutM5Zalr4",
  "number": 29922,
  "title": "Registration for reflection with unsafeAllocated",
  "labels": [
    {
      "id": 985346622,
      "node_id": "MDU6TGFiZWw5ODUzNDY2MjI=",
      "url": "https://api.github.com/repos/quarkusio/quarkus/labels/kind/enhancement",
      "name": "kind/enhancement",
      "color": "a2eeef",
      "default": false,
      "description": "New feature or request"
    },
    {
      "id": 2497075451,
      "node_id": "MDU6TGFiZWwyNDk3MDc1NDUx",
      "url": "https://api.github.com/repos/quarkusio/quarkus/labels/area/native-image",
      "name": "area/native-image",
      "color": "0366d6",
      "default": false,
      "description": ""
    }
  ],
  "state": "closed",
  "locked": false,
  "milestone": {
    "url": "https://api.github.com/repos/quarkusio/quarkus/milestones/235",
    "html_url": "https://github.com/quarkusio/quarkus/milestone/235",
    "labels_url": "https://api.github.com/repos/quarkusio/quarkus/milestones/235/labels",
    "id": 9025446,
    "node_id": "MI_kwDOCFbutM4Aibem",
    "number": 235,
    "title": "3.0.0.Alpha5",
    "description": "",
    "creator": {
      "login": "gsmet",
      "id": 1279749,
      "node_id": "MDQ6VXNlcjEyNzk3NDk=",
      "avatar_url": "https://avatars.githubusercontent.com/u/1279749?v=4",
      "gravatar_id": "",
      "url": "https://api.github.com/users/gsmet",
      "html_url": "https://github.com/gsmet",
      "followers_url": "https://api.github.com/users/gsmet/followers",
      "following_url": "https://api.github.com/users/gsmet/following{/other_user}",
      "gists_url": "https://api.github.com/users/gsmet/gists{/gist_id}",
      "starred_url": "https://api.github.com/users/gsmet/starred{/owner}{/repo}",
      "subscriptions_url": "https://api.github.com/users/gsmet/subscriptions",
      "organizations_url": "https://api.github.com/users/gsmet/orgs",
      "repos_url": "https://api.github.com/users/gsmet/repos",
      "events_url": "https://api.github.com/users/gsmet/events{/privacy}",
      "received_events_url": "https://api.github.com/users/gsmet/received_events",
      "type": "User",
      "site_admin": false
    },
    "open_issues": 0,
    "closed_issues": 253,
    "state": "closed",
    "created_at": "2023-02-09T14:26:03Z",
    "updated_at": "2023-11-12T17:44:08Z",
    "due_on": null,
    "closed_at": "2023-03-08T15:10:59Z"
  },
  "comments": 3,
  "created_at": "2022-12-16T12:39:22Z",
  "updated_at": "2023-02-16T13:13:56Z",
  "closed_at": "2023-02-16T13:13:52Z",
  "active_lock_reason": null,
  "body": "### Description\n\nFollows up https://github.com/apache/camel-quarkus/issues/4284#issuecomment-1354604958 where Mandrel hits us registering a class for reflection with `unsafeAllocated=true` which is currently not possible using Quarkus BuildItems.\r\n\r\nSee also https://www.graalvm.org/22.2/reference-manual/native-image/metadata/#specifying-reflection-metadata-in-json\r\n\r\n\r\n\r\n\n\n### Implementation ideas\n\n`ReflectiveClassBuildItem` (and perhaps other build items handling reflection registrations) should get a support for this.",
  "reactions": {
    "url": "https://api.github.com/repos/quarkusio/quarkus/issues/29922/reactions",
    "total_count": 0,
    "+1": 0,
    "-1": 0,
    "laugh": 0,
    "hooray": 0,
    "confused": 0,
    "heart": 0,
    "rocket": 0,
    "eyes": 0
  },
  "timeline_url": "https://api.github.com/repos/quarkusio/quarkus/issues/29922/timeline",
  "performed_via_github_app": null,
  "state_reason": "completed"
}
