{
  "url": "https://api.github.com/repos/quarkusio/quarkus/issues/30919",
  "repository_url": "https://api.github.com/repos/quarkusio/quarkus",
  "labels_url": "https://api.github.com/repos/quarkusio/quarkus/issues/30919/labels{/name}",
  "comments_url": "https://api.github.com/repos/quarkusio/quarkus/issues/30919/comments",
  "events_url": "https://api.github.com/repos/quarkusio/quarkus/issues/30919/events",
  "html_url": "https://github.com/quarkusio/quarkus/issues/30919",
  "id": 1572330808,
  "node_id": "I_kwDOCFbutM5dt904",
  "number": 30919,
  "title": "Compilation to native fails, when quarkus-smallrye-openapi is included",
  "labels": [
    {
      "id": 985346620,
      "node_id": "MDU6TGFiZWw5ODUzNDY2MjA=",
      "url": "https://api.github.com/repos/quarkusio/quarkus/labels/kind/bug",
      "name": "kind/bug",
      "color": "d73a4a",
      "default": false,
      "description": "Something isn't working"
    },
    {
      "id": 1336727006,
      "node_id": "MDU6TGFiZWwxMzM2NzI3MDA2",
      "url": "https://api.github.com/repos/quarkusio/quarkus/labels/area/openapi",
      "name": "area/openapi",
      "color": "0366d6",
      "default": false,
      "description": ""
    },
    {
      "id": 2497075451,
      "node_id": "MDU6TGFiZWwyNDk3MDc1NDUx",
      "url": "https://api.github.com/repos/quarkusio/quarkus/labels/area/native-image",
      "name": "area/native-image",
      "color": "0366d6",
      "default": false,
      "description": ""
    }
  ],
  "state": "closed",
  "locked": false,
  "milestone": {
    "url": "https://api.github.com/repos/quarkusio/quarkus/milestones/234",
    "html_url": "https://github.com/quarkusio/quarkus/milestone/234",
    "labels_url": "https://api.github.com/repos/quarkusio/quarkus/milestones/234/labels",
    "id": 9024843,
    "node_id": "MI_kwDOCFbutM4AibVL",
    "number": 234,
    "title": "2.13.8.Final",
    "description": "",
    "creator": {
      "login": "gsmet",
      "id": 1279749,
      "node_id": "MDQ6VXNlcjEyNzk3NDk=",
      "avatar_url": "https://avatars.githubusercontent.com/u/1279749?v=4",
      "gravatar_id": "",
      "url": "https://api.github.com/users/gsmet",
      "html_url": "https://github.com/gsmet",
      "followers_url": "https://api.github.com/users/gsmet/followers",
      "following_url": "https://api.github.com/users/gsmet/following{/other_user}",
      "gists_url": "https://api.github.com/users/gsmet/gists{/gist_id}",
      "starred_url": "https://api.github.com/users/gsmet/starred{/owner}{/repo}",
      "subscriptions_url": "https://api.github.com/users/gsmet/subscriptions",
      "organizations_url": "https://api.github.com/users/gsmet/orgs",
      "repos_url": "https://api.github.com/users/gsmet/repos",
      "events_url": "https://api.github.com/users/gsmet/events{/privacy}",
      "received_events_url": "https://api.github.com/users/gsmet/received_events",
      "type": "User",
      "site_admin": false
    },
    "open_issues": 0,
    "closed_issues": 58,
    "state": "closed",
    "created_at": "2023-02-09T12:37:45Z",
    "updated_at": "2023-05-25T12:39:39Z",
    "due_on": null,
    "closed_at": "2023-05-25T12:39:39Z"
  },
  "comments": 10,
  "created_at": "2023-02-06T10:43:20Z",
  "updated_at": "2023-05-09T09:23:54Z",
  "closed_at": "2023-02-07T07:33:38Z",
  "active_lock_reason": null,
  "body": "### Describe the bug\r\n\r\nI have an application, which uses `quarkus-smallrye-openapi` dependency. The application works flawlessly in JVM mode, but fails during `Performing analysis` phase in Native mode. Experimenting shows, that the app fails simply when that dependency is included in pom.\r\n\r\n### Expected behavior\r\n\r\nApp should work in both JVM and Native modes\r\n\r\n### Actual behavior\r\n\r\n```\r\n[2/7] Performing analysis...  []                                                                        (43.2s @ 1.13GB)\r\n  11,264 (91.32%) of 12,334 classes reachable\r\n  14,775 (57.48%) of 25,705 fields reachable\r\n  47,410 (80.62%) of 58,807 methods reachable\r\n     541 classes,     0 fields, and     0 methods registered for reflection\r\n\r\nError: java.util.concurrent.ExecutionException: com.oracle.svm.core.util.VMError$HostedError: java.lang.reflect.InvocationTargetException\r\ncom.oracle.graal.pointsto.util.AnalysisError: java.util.concurrent.ExecutionException: com.oracle.svm.core.util.VMError$HostedError: java.lang.reflect.InvocationTargetException\r\n\tat org.graalvm.nativeimage.pointsto/com.oracle.graal.pointsto.util.AnalysisError.shouldNotReachHere(AnalysisError.java:173)\r\n\tat org.graalvm.nativeimage.pointsto/com.oracle.graal.pointsto.util.AnalysisFuture.ensureDone(AnalysisFuture.java:66)\r\n\tat org.graalvm.nativeimage.pointsto/com.oracle.graal.pointsto.heap.ImageHeapScanner.lambda$postTask$12(ImageHeapScanner.java:663)\r\n\tat org.graalvm.nativeimage.pointsto/com.oracle.graal.pointsto.util.CompletionExecutor.executeCommand(CompletionExecutor.java:193)\r\n\tat org.graalvm.nativeimage.pointsto/com.oracle.graal.pointsto.util.CompletionExecutor.lambda$executeService$0(CompletionExecutor.java:177)\r\n\tat java.base/java.util.concurrent.ForkJoinTask$RunnableExecuteAction.exec(ForkJoinTask.java:1395)\r\n\tat java.base/java.util.concurrent.ForkJoinTask.doExec(ForkJoinTask.java:373)\r\n\tat java.base/java.util.concurrent.ForkJoinPool$WorkQueue.topLevelExec(ForkJoinPool.java:1182)\r\n\tat java.base/java.util.concurrent.ForkJoinPool.scan(ForkJoinPool.java:1655)\r\n\tat java.base/java.util.concurrent.ForkJoinPool.runWorker(ForkJoinPool.java:1622)\r\n\tat java.base/java.util.concurrent.ForkJoinWorkerThread.run(ForkJoinWorkerThread.java:165)\r\nCaused by: java.util.concurrent.ExecutionException: com.oracle.svm.core.util.VMError$HostedError: java.lang.reflect.InvocationTargetException\r\n\tat java.base/java.util.concurrent.FutureTask.report(FutureTask.java:122)\r\n\tat java.base/java.util.concurrent.FutureTask.get(FutureTask.java:191)\r\n\tat org.graalvm.nativeimage.pointsto/com.oracle.graal.pointsto.util.AnalysisFuture.ensureDone(AnalysisFuture.java:64)\r\n\t... 9 more\r\nCaused by: com.oracle.svm.core.util.VMError$HostedError: java.lang.reflect.InvocationTargetException\r\n\tat org.graalvm.nativeimage.builder/com.oracle.svm.core.util.VMError.shouldNotReachHere(VMError.java:72)\r\n\tat org.graalvm.nativeimage.builder/com.oracle.svm.hosted.annotation.AnnotationSubstitutionField.readValue(AnnotationSubstitutionField.java:131)\r\n\tat org.graalvm.nativeimage.builder/com.oracle.svm.hosted.ameta.AnalysisConstantReflectionProvider.readHostedFieldValue(AnalysisConstantReflectionProvider.java:123)\r\n\tat org.graalvm.nativeimage.builder/com.oracle.svm.hosted.heap.SVMImageHeapScanner.readHostedFieldValue(SVMImageHeapScanner.java:122)\r\n\tat org.graalvm.nativeimage.pointsto/com.oracle.graal.pointsto.heap.ImageHeapScanner.createImageHeapObject(ImageHeapScanner.java:277)\r\n\tat org.graalvm.nativeimage.pointsto/com.oracle.graal.pointsto.heap.ImageHeapScanner.lambda$getOrCreateConstantReachableTask$2(ImageHeapScanner.java:203)\r\n\tat java.base/java.util.concurrent.FutureTask.run(FutureTask.java:264)\r\n\tat org.graalvm.nativeimage.pointsto/com.oracle.graal.pointsto.util.AnalysisFuture.ensureDone(AnalysisFuture.java:63)\r\n\tat org.graalvm.nativeimage.pointsto/com.oracle.graal.pointsto.heap.ImageHeapScanner.getOrCreateConstantReachableTask(ImageHeapScanner.java:215)\r\n\tat org.graalvm.nativeimage.builder/com.oracle.svm.hosted.heap.SVMImageHeapScanner.getOrCreateConstantReachableTask(SVMImageHeapScanner.java:95)\r\n\tat org.graalvm.nativeimage.pointsto/com.oracle.graal.pointsto.heap.ImageHeapScanner.markConstantReachable(ImageHeapScanner.java:179)\r\n\tat org.graalvm.nativeimage.pointsto/com.oracle.graal.pointsto.heap.ImageHeapScanner.onFieldValueReachable(ImageHeapScanner.java:357)\r\n\tat org.graalvm.nativeimage.pointsto/com.oracle.graal.pointsto.heap.ImageHeapScanner.lambda$createImageHeapObject$3(ImageHeapScanner.java:284)\r\n\tat java.base/java.util.concurrent.FutureTask.run(FutureTask.java:264)\r\n\tat org.graalvm.nativeimage.pointsto/com.oracle.graal.pointsto.util.AnalysisFuture.ensureDone(AnalysisFuture.java:63)\r\n\t... 9 more\r\nCaused by: java.lang.reflect.InvocationTargetException\r\n\tat java.base/jdk.internal.reflect.NativeMethodAccessorImpl.invoke0(Native Method)\r\n\tat java.base/jdk.internal.reflect.NativeMethodAccessorImpl.invoke(NativeMethodAccessorImpl.java:77)\r\n\tat java.base/jdk.internal.reflect.DelegatingMethodAccessorImpl.invoke(DelegatingMethodAccessorImpl.java:43)\r\n\tat java.base/java.lang.reflect.Method.invoke(Method.java:568)\r\n\tat org.graalvm.nativeimage.builder/com.oracle.svm.hosted.annotation.AnnotationSubstitutionField.readValue(AnnotationSubstitutionField.java:114)\r\n\t... 22 more\r\nCaused by: java.lang.annotation.AnnotationTypeMismatchException: Incorrectly typed data found for annotation element public abstract org.eclipse.microprofile.openapi.annotations.enums.SchemaType org.eclipse.microprofile.openapi.annotations.media.Schema.type() (Found data of type java.lang.String[ARRAY])\r\n\tat java.base/sun.reflect.annotation.AnnotationTypeMismatchExceptionProxy.generateException(AnnotationTypeMismatchExceptionProxy.java:59)\r\n\tat java.base/sun.reflect.annotation.AnnotationInvocationHandler.invoke(AnnotationInvocationHandler.java:89)\r\n\tat org.graalvm.nativeimage.builder/com.oracle.svm.core.SubstrateAnnotationInvocationHandler.invoke(SubstrateAnnotationInvocationHandler.java:52)\r\n\tat jdk.proxy4/jdk.proxy4.$Proxy141.type(Unknown Source)\r\n\t... 27 more\r\n\r\n```\r\n\r\n### How to Reproduce?\r\n\r\n1. `git clone git@github.com:fedinskiy/quarkus-test-suite.git -b reproducer/openapi-failure`\r\n2. `cd quarkus-test-suite/spring/spring-data`\r\n3. `mvn clean verify -Dnative -Dquarkus.platform.version=2.16.1.Final -Pfail`\r\n4. `mvn clean verify -Dnative -Dquarkus.platform.version=2.16.1.Final` — this compiles, but expectedly fails during test phase due to lack of `q/openapi` endpoint\r\n\r\n### Output of `uname -a` or `ver`\r\n\r\n6.0.18-300.fc37.x86_64\r\n\r\n### Output of `java -version`\r\n\r\n17.0.6, vendor: GraalVM Community\r\n\r\n### GraalVM version (if different from Java)\r\n\r\n_No response_\r\n\r\n### Quarkus version or git rev\r\n\r\n2.16.1.Final\r\n\r\n### Build tool (ie. output of `mvnw --version` or `gradlew --version`)\r\n\r\nApache Maven 3.8.6 (84538c9988a25aec085021c365c560670ad80f63)\r\n\r\n### Additional information\r\n\r\n_No response_",
  "reactions": {
    "url": "https://api.github.com/repos/quarkusio/quarkus/issues/30919/reactions",
    "total_count": 0,
    "+1": 0,
    "-1": 0,
    "laugh": 0,
    "hooray": 0,
    "confused": 0,
    "heart": 0,
    "rocket": 0,
    "eyes": 0
  },
  "timeline_url": "https://api.github.com/repos/quarkusio/quarkus/issues/30919/timeline",
  "performed_via_github_app": null,
  "state_reason": "completed"
}
