{
  "url": "https://api.github.com/repos/quarkusio/quarkus/issues/40462",
  "repository_url": "https://api.github.com/repos/quarkusio/quarkus",
  "labels_url": "https://api.github.com/repos/quarkusio/quarkus/issues/40462/labels{/name}",
  "comments_url": "https://api.github.com/repos/quarkusio/quarkus/issues/40462/comments",
  "events_url": "https://api.github.com/repos/quarkusio/quarkus/issues/40462/events",
  "html_url": "https://github.com/quarkusio/quarkus/issues/40462",
  "id": 2279287605,
  "node_id": "I_kwDOCFbutM6H2ys1",
  "number": 40462,
  "title": "codestart are using legacy properties still",
  "labels": [
    {
      "id": 985346620,
      "node_id": "MDU6TGFiZWw5ODUzNDY2MjA=",
      "url": "https://api.github.com/repos/quarkusio/quarkus/labels/kind/bug",
      "name": "kind/bug",
      "color": "d73a4a",
      "default": false,
      "description": "Something isn't working"
    },
    {
      "id": 2244490669,
      "node_id": "MDU6TGFiZWwyMjQ0NDkwNjY5",
      "url": "https://api.github.com/repos/quarkusio/quarkus/labels/area/codestarts",
      "name": "area/codestarts",
      "color": "0366d6",
      "default": false,
      "description": ""
    }
  ],
  "state": "closed",
  "locked": false,
  "milestone": null,
  "comments": 3,
  "created_at": "2024-05-05T02:18:43Z",
  "updated_at": "2024-05-12T00:33:17Z",
  "closed_at": "2024-05-12T00:33:17Z",
  "active_lock_reason": null,
  "body": "### Describe the bug\n\nwhen generating a 3.10 project via code.quarkus.io\r\nthe pom.xml still has;\r\n`<quarkus.package.type>native</quarkus.package.type>`\r\ninstead of\r\n`<quarkus.native.enabled>true<quarkus.native.enabled>`\r\n\r\nand the readme.md still has\r\n`./mvnw package -Dquarkus.package.type=uber-jar`\r\ninstead of\r\n`./mvnw package -Dquarkus.package.jar.type=uber-jar`\r\n\r\nI looked at the main branch and the 3.10 branch and it looks fine in terms of the above so unsure why this happens.\n\n### Expected behavior\n\nnew properties are used\n\n### Actual behavior\n\nlegacy properties are used\n\n### How to Reproduce?\n\n1- go to https://code.quarkus.io/\r\n2- click generate and download the app\r\n3- observe the pom.xml and README.md\n\n### Output of `uname -a` or `ver`\n\n_No response_\n\n### Output of `java -version`\n\n_No response_\n\n### Quarkus version or git rev\n\n_No response_\n\n### Build tool (ie. output of `mvnw --version` or `gradlew --version`)\n\n_No response_\n\n### Additional information\n\n_No response_",
  "reactions": {
    "url": "https://api.github.com/repos/quarkusio/quarkus/issues/40462/reactions",
    "total_count": 0,
    "+1": 0,
    "-1": 0,
    "laugh": 0,
    "hooray": 0,
    "confused": 0,
    "heart": 0,
    "rocket": 0,
    "eyes": 0
  },
  "timeline_url": "https://api.github.com/repos/quarkusio/quarkus/issues/40462/timeline",
  "performed_via_github_app": null,
  "state_reason": "completed"
}
