{
  "url": "https://api.github.com/repos/quarkusio/quarkus/issues/42582",
  "repository_url": "https://api.github.com/repos/quarkusio/quarkus",
  "labels_url": "https://api.github.com/repos/quarkusio/quarkus/issues/42582/labels{/name}",
  "comments_url": "https://api.github.com/repos/quarkusio/quarkus/issues/42582/comments",
  "events_url": "https://api.github.com/repos/quarkusio/quarkus/issues/42582/events",
  "html_url": "https://github.com/quarkusio/quarkus/issues/42582",
  "id": 2469646431,
  "node_id": "I_kwDOCFbutM6TM9Bf",
  "number": 42582,
  "title": "[Feature Request] Infinispan as Hibernate second-level cache provider",
  "labels": [
    {
      "id": 985346622,
      "node_id": "MDU6TGFiZWw5ODUzNDY2MjI=",
      "url": "https://api.github.com/repos/quarkusio/quarkus/labels/kind/enhancement",
      "name": "kind/enhancement",
      "color": "a2eeef",
      "default": false,
      "description": "New feature or request"
    },
    {
      "id": 1282122953,
      "node_id": "MDU6TGFiZWwxMjgyMTIyOTUz",
      "url": "https://api.github.com/repos/quarkusio/quarkus/labels/area/infinispan",
      "name": "area/infinispan",
      "color": "0366d6",
      "default": false,
      "description": "Infinispan"
    },
    {
      "id": 1425555736,
      "node_id": "MDU6TGFiZWwxNDI1NTU1NzM2",
      "url": "https://api.github.com/repos/quarkusio/quarkus/labels/area/hibernate-orm",
      "name": "area/hibernate-orm",
      "color": "0366d6",
      "default": false,
      "description": "Hibernate ORM"
    },
    {
      "id": 1808747697,
      "node_id": "MDU6TGFiZWwxODA4NzQ3Njk3",
      "url": "https://api.github.com/repos/quarkusio/quarkus/labels/area/cache",
      "name": "area/cache",
      "color": "0366d6",
      "default": false,
      "description": ""
    }
  ],
  "state": "open",
  "locked": false,
  "milestone": null,
  "comments": 7,
  "created_at": "2024-08-16T07:07:03Z",
  "updated_at": "2024-08-28T08:36:38Z",
  "closed_at": null,
  "active_lock_reason": null,
  "body": "### Description\n\nFollowing https://github.com/quarkusio/quarkus/issues/42541\r\n\r\nQuarkus + Hibernate works great!  \r\nQuarkus + Infinispan works great!  \r\n[Hibernate + Infinispan](https://infinispan.org/docs/stable/titles/hibernate/hibernate.html) works great!\r\n\r\nAs Quarkus is microservices-oriented, we usually have multiple instances of the application so, it would be nice to have a distributed cache like Infinispan as Hibernate second-level cache provider :-)\n\n### Implementation ideas\n\n_No response_",
  "reactions": {
    "url": "https://api.github.com/repos/quarkusio/quarkus/issues/42582/reactions",
    "total_count": 0,
    "+1": 0,
    "-1": 0,
    "laugh": 0,
    "hooray": 0,
    "confused": 0,
    "heart": 0,
    "rocket": 0,
    "eyes": 0
  },
  "timeline_url": "https://api.github.com/repos/quarkusio/quarkus/issues/42582/timeline",
  "performed_via_github_app": null,
  "state_reason": null
}
